yuncheng_util_pkg/__init__.py
yuncheng_util_pkg/analysis_pic.py
yuncheng_util_pkg/analysis_pipeline.py
yuncheng_util_pkg/analysis_ratio.py
yuncheng_util_pkg/check_color_board.py
yuncheng_util_pkg/compare_two_al_result.py
yuncheng_util_pkg/compare_yuncheng_al.py
yuncheng_util_pkg/db_util.py
yuncheng_util_pkg/util.py
yuncheng_util_pkg/util_file.py
yuncheng_util_pkg/util_net.py
yuncheng_util_pkg/yuncheng_al_class.py
yuncheng_util_pkg/yuncheng_label.py
yuncheng_util_pkg-1.3.dist-info/METADATA
yuncheng_util_pkg-1.3.dist-info/WHEEL
yuncheng_util_pkg-1.3.dist-info/top_level.txt
yuncheng_util_pkg-1.3.dist-info/RECORD
