Metadata-Version: 2.1
Name: yuncheng-util-pkg
Version: 1.3
Summary: UNKNOWN
Home-page: https://e.coding.net/yuncheng/yuncheng-python-package/python-util.git
Author: wangwei
Author-email: wangwei@ikangtai.com
License: UNKNOWN
Platform: any
Requires-Python: >=3.6
Requires-Dist: requests (>=2.20.0)
Requires-Dist: matplotlib
Requires-Dist: opencv-python
